<?xml version="1.0" encoding="utf-8"?>
<MediaBackup xmlns:xsi="http://www.w3.org/2001/XMLSchema-instance" xmlns:xsd="http://www.w3.org/2001/XMLSchema">
  <PushoverUserKey>InsertYourPushoverUserKeyHere</PushoverUserKey>
  <PushoverAppToken>InsertYourPushoverAppTokenHere</PushoverAppToken>
  <!-- When true a backup scan will run when the app starts -->
  <StartScheduledBackup>false</StartScheduledBackup>
  <!-- A bigger percentage difference than this and the backup stops -->
  <DifferenceInFileCountAllowedPercentage>2</DifferenceInFileCountAllowedPercentage>
  <!--  ScheduledBackupStartTime as hh:mm -->
  <ScheduledBackupStartTime>11:00</ScheduledBackupStartTime>
  <!-- MinimumCriticalMasterFolderSpace in MB -->
  <MinimumCriticalMasterFolderSpace>200</MinimumCriticalMasterFolderSpace>
  <!-- MinimumCriticalBackupDiskSpace in MB -->
  <MinimumCriticalBackupDiskSpace>1</MinimumCriticalBackupDiskSpace>
  <!-- After this many days the backup warns to check the disks again -->
  <DaysToReportOldBackupDisks>90</DaysToReportOldBackupDisks>
  <!-- MinimumFreeSpaceToLeaveOnBackupDrive in MB -->
  <MinimumFreeSpaceToLeaveOnBackupDrive>10</MinimumFreeSpaceToLeaveOnBackupDrive>
  <!-- Minimum read speed in MB/s -->
  <MinimumMasterFolderReadSpeed>30</MinimumMasterFolderReadSpeed>
  <!-- Minimum write speed in MB/s -->
  <MinimumMasterFolderWriteSpeed>50</MinimumMasterFolderWriteSpeed>
  <MasterFolders>
    <!-- List each UNC path that you want to scan for files to backup here -->
    <MasterFolder>\\nas1\assets1</MasterFolder>
    <MasterFolder>\\nas1\assets2</MasterFolder>
    <MasterFolder>\\nas1\assets3</MasterFolder>
    <MasterFolder>\\nas1\assets4</MasterFolder>
    <MasterFolder>\\nas2\assets1</MasterFolder>
    <MasterFolder>\\nas2\assets2</MasterFolder>
    <MasterFolder>\\nas2\assets3</MasterFolder>
    <MasterFolder>\\nas2\assets4</MasterFolder>
    <MasterFolder>\\nas3\assets1</MasterFolder>
    <MasterFolder>\\nas3\assets2</MasterFolder>
    <MasterFolder>\\nas3\assets3</MasterFolder>
    <MasterFolder>\\nas3\assets4</MasterFolder>
    <MasterFolder>\\nas4\assets1</MasterFolder>
    <MasterFolder>\\nas4\assets2</MasterFolder>
    <MasterFolder>\\nas4\assets3</MasterFolder>
    <MasterFolder>\\nas4\assets4</MasterFolder>
    <MasterFolder>\\nas5\assets1</MasterFolder>
    <MasterFolder>\\nas5\assets2</MasterFolder>
    <MasterFolder>\\nas5\assets3</MasterFolder>
    <MasterFolder>\\nas5\assets4</MasterFolder>
  </MasterFolders>
  <IndexFolders>
    <!-- These are the subfolders that will be searched in the shares above -->
    <IndexFolder>_Audio Books</IndexFolder>
    <IndexFolder>_Comedy</IndexFolder>
    <IndexFolder>_Concerts</IndexFolder>
    <IndexFolder>_MMA</IndexFolder>
    <IndexFolder>_Movies</IndexFolder>
    <IndexFolder>_Music</IndexFolder>
    <IndexFolder>_Other</IndexFolder>
    <IndexFolder>_Pictures</IndexFolder>
    <IndexFolder>_Playlists</IndexFolder>
    <IndexFolder>_Sport</IndexFolder>
    <IndexFolder>_TV</IndexFolder>
    <IndexFolder>_Videos</IndexFolder>
  </IndexFolders>
  <Filters>
    <!-- RegEx's of file to ignore when executing a scan -->
    <FilterRegEx>!*.bup</FilterRegEx>
    <FilterRegEx>!*.db</FilterRegEx>
    <FilterRegEx>!*.dna</FilterRegEx>
    <FilterRegEx>!*.ds_store</FilterRegEx>
    <FilterRegEx>!*.ifo</FilterRegEx>
    <FilterRegEx>!*.ign</FilterRegEx>
    <FilterRegEx>!*.ini</FilterRegEx>
    <FilterRegEx>!*.plexignore</FilterRegEx>
    <FilterRegEx>!*.txt</FilterRegEx>
    <FilterRegEx>!*.vob</FilterRegEx>
    <FilterRegEx>!*.xml</FilterRegEx>
  </Filters>
  <VideoFoldersFormatsAllowed>
    <VideoFormat>.mkv</VideoFormat>
    <VideoFormat>.mp4</VideoFormat>
    <VideoFormat>.mpg</VideoFormat>
    <VideoFormat>.mpeg</VideoFormat>
    <VideoFormat>.ts</VideoFormat>
    <VideoFormat>.srt</VideoFormat>
    <VideoFormat>.avi</VideoFormat>
  </VideoFoldersFormatsAllowed>
  <EditionsAllowed>
    <Edition>10th Anniversary Edition</Edition>
    <Edition>20th Anniversary Edition</Edition>
    <Edition>25th Anniversary Edition</Edition>
    <Edition>30th Anniversary Edition</Edition>
    <Edition>40th Anniversary Edition</Edition>
    <Edition>50th Anniversary Edition</Edition>
    <Edition>60th Anniversary Edition</Edition>
    <Edition>70th Anniversary Edition</Edition>
    <Edition>4K Edition</Edition>
    <Edition>Bluray Edition</Edition>
    <Edition>Chronological Edition</Edition>
    <Edition>Collectors Edition</Edition>
    <Edition>Criterion Collection</Edition>
    <Edition>Diamond Edition</Edition>
    <Edition>Directors Cut</Edition>
    <Edition>DVD Edition</Edition>
    <Edition>Extended Edition</Edition>
    <Edition>IMAX Edition</Edition>
    <Edition>Redux Edition</Edition>
    <Edition>Remastered Edition</Edition>
    <Edition>Restored Edition</Edition>
    <Edition>Special Edition</Edition>
    <Edition>The Complete Extended Edition</Edition>
    <Edition>The Final Cut</Edition>
    <Edition>The Godfather Coda</Edition>
    <Edition>The Richard Donner Cut</Edition>
    <Edition>Theatrical Edition</Edition>
    <Edition>Ultimate Edition</Edition>
    <Edition>Uncut Edition</Edition>
    <Edition>Unrated Edition</Edition>
  </EditionsAllowed>
  <DisksToSkipOnRestore>
    <DiskToSkip>Backup 1</DiskToSkip>
    <DiskToSkip>Backup 2</DiskToSkip>
    <DiskToSkip>Backup 3</DiskToSkip>
    <DiskToSkip>Backup 4</DiskToSkip>
  </DisksToSkipOnRestore>
  <BackupFiles>
    <!-- Sample BackupFile entries -->
    <BackupFile>
      <Path>The Unit\The Unit Season 1\The Unit s01.e01.mkv</Path>
      <MasterFolder>\\reevesandyc6cc\testdata</MasterFolder>
      <IndexFolder>_TV Series</IndexFolder>
      <LastWriteTime>2016-08-31T20:23:12.4340183+01:00</LastWriteTime>
      <Length>27</Length>
      <Hash>736386c78791fe1c4decd71b63150163</Hash>
    </BackupFile>
    <BackupFile>
      <Path>The Unit\The Unit Season 1\The Unit s01.e02.mkv</Path>
      <MasterFolder>\\reevesandyc6cc\testdata</MasterFolder>
      <IndexFolder>_TV Series</IndexFolder>
      <LastWriteTime>2016-08-31T20:23:12.4340183+01:00</LastWriteTime>
      <Length>27</Length>
      <Hash>736386c78791fe1c4decd71b63150163</Hash>
    </BackupFile>
  </BackupFiles>
</MediaBackup>